stvis/__init__.py
stvis-0.0.2.dist-info/LICENSE
stvis-0.0.2.dist-info/METADATA
stvis-0.0.2.dist-info/WHEEL
stvis-0.0.2.dist-info/top_level.txt
stvis-0.0.2.dist-info/RECORD
