Metadata-Version: 2.1
Name: stvis
Version: 0.0.2
Summary: Streamlit component for pyvis
Home-page: 
Author: Jose Manuel Napoles Duarte
Author-email: jnapoles@uach.mx
License: UNKNOWN
Platform: UNKNOWN
Requires-Python: >=3.6
License-File: LICENSE
